data_explorer/__init__.py
data_explorer/getter.py
worldbank_ac-0.1.0.dist-info/METADATA
worldbank_ac-0.1.0.dist-info/WHEEL
worldbank_ac-0.1.0.dist-info/top_level.txt
worldbank_ac-0.1.0.dist-info/RECORD
