Metadata-Version: 2.4
Name: worldbank-ac
Version: 0.1.0
Summary: Package Python pour récupérer les données économiques du Sénégal via l'API World Bank
Author-email: arielchrist <achristngato@groupeisi.com>
License: MIT
Project-URL: Homepage, https://github.com/ArielChrist/
Project-URL: Repository, https://github.com/ArielChrist/
Project-URL: Issues, https://github.com/ArielChrist/slugify-fr/issues
Requires-Python: >=3.7
Requires-Dist: pandas
